{
  "address": "FtqmpF6VR9C4hxfboSD7VdPxYXRz4G395b6yLvoBALT1",
  "metadata": {
    "name": "daily_auction",
    "version": "0.1.0",
    "spec": "0.1.0",
    "description": "Created with Anchor"
  },
  "instructions": [
    {
      "name": "bid",
      "discriminator": [
        199,
        56,
        85,
        38,
        146,
        243,
        37,
        158
      ],
      "accounts": [
        {
          "name": "auction",
          "writable": true,
          "pda": {
            "seeds": [
              {
                "kind": "const",
                "value": [
                  97,
                  117,
                  99,
                  116,
                  105,
                  111,
                  110
                ]
              }
            ]
          }
        },
        {
          "name": "bidder",
          "writable": true,
          "signer": true
        },
        {
          "name": "old_bidder",
          "writable": true
        },
        {
          "name": "system_program",
          "address": "11111111111111111111111111111111"
        }
      ],
      "args": [
        {
          "name": "amount",
          "type": "u64"
        },
        {
          "name": "new_content",
          "type": "string"
        }
      ]
    },
    {
      "name": "end_and_start_auction",
      "discriminator": [
        17,
        95,
        142,
        94,
        169,
        102,
        175,
        32
      ],
      "accounts": [
        {
          "name": "auction",
          "writable": true,
          "pda": {
            "seeds": [
              {
                "kind": "const",
                "value": [
                  97,
                  117,
                  99,
                  116,
                  105,
                  111,
                  110
                ]
              }
            ]
          }
        },
        {
          "name": "authority",
          "writable": true,
          "signer": true,
          "relations": [
            "auction"
          ]
        },
        {
          "name": "system_program",
          "address": "11111111111111111111111111111111"
        }
      ],
      "args": [
        {
          "name": "new_content",
          "type": "string"
        }
      ]
    },
    {
      "name": "end_auction",
      "discriminator": [
        252,
        110,
        101,
        234,
        66,
        104,
        28,
        87
      ],
      "accounts": [
        {
          "name": "auction",
          "writable": true,
          "pda": {
            "seeds": [
              {
                "kind": "const",
                "value": [
                  97,
                  117,
                  99,
                  116,
                  105,
                  111,
                  110
                ]
              }
            ]
          }
        },
        {
          "name": "authority",
          "writable": true,
          "relations": [
            "auction"
          ]
        },
        {
          "name": "system_program",
          "address": "11111111111111111111111111111111"
        }
      ],
      "args": []
    },
    {
      "name": "initialize",
      "discriminator": [
        175,
        175,
        109,
        31,
        13,
        152,
        155,
        237
      ],
      "accounts": [
        {
          "name": "auction",
          "writable": true,
          "pda": {
            "seeds": [
              {
                "kind": "const",
                "value": [
                  97,
                  117,
                  99,
                  116,
                  105,
                  111,
                  110
                ]
              }
            ]
          }
        },
        {
          "name": "authority",
          "writable": true,
          "signer": true
        },
        {
          "name": "system_program",
          "address": "11111111111111111111111111111111"
        }
      ],
      "args": [
        {
          "name": "initial_content",
          "type": "string"
        }
      ]
    },
    {
      "name": "set_auction_number",
      "discriminator": [
        28,
        133,
        185,
        121,
        127,
        157,
        75,
        180
      ],
      "accounts": [
        {
          "name": "auction",
          "writable": true,
          "pda": {
            "seeds": [
              {
                "kind": "const",
                "value": [
                  97,
                  117,
                  99,
                  116,
                  105,
                  111,
                  110
                ]
              }
            ]
          }
        },
        {
          "name": "authority",
          "writable": true,
          "signer": true,
          "relations": [
            "auction"
          ]
        },
        {
          "name": "system_program",
          "address": "11111111111111111111111111111111"
        }
      ],
      "args": [
        {
          "name": "auction_number",
          "type": "u64"
        }
      ]
    },
    {
      "name": "set_authority",
      "discriminator": [
        133,
        250,
        37,
        21,
        110,
        163,
        26,
        121
      ],
      "accounts": [
        {
          "name": "auction",
          "writable": true,
          "pda": {
            "seeds": [
              {
                "kind": "const",
                "value": [
                  97,
                  117,
                  99,
                  116,
                  105,
                  111,
                  110
                ]
              }
            ]
          }
        },
        {
          "name": "authority",
          "signer": true,
          "relations": [
            "auction"
          ]
        }
      ],
      "args": [
        {
          "name": "new_authority",
          "type": "pubkey"
        }
      ]
    },
    {
      "name": "start_auction",
      "discriminator": [
        255,
        2,
        149,
        136,
        148,
        125,
        65,
        195
      ],
      "accounts": [
        {
          "name": "auction",
          "writable": true,
          "pda": {
            "seeds": [
              {
                "kind": "const",
                "value": [
                  97,
                  117,
                  99,
                  116,
                  105,
                  111,
                  110
                ]
              }
            ]
          }
        },
        {
          "name": "authority",
          "signer": true,
          "relations": [
            "auction"
          ]
        }
      ],
      "args": [
        {
          "name": "new_content",
          "type": "string"
        }
      ]
    }
  ],
  "accounts": [
    {
      "name": "Auction",
      "discriminator": [
        218,
        94,
        247,
        242,
        126,
        233,
        131,
        81
      ]
    }
  ],
  "events": [
    {
      "name": "AuctionEnded",
      "discriminator": [
        91,
        165,
        139,
        202,
        204,
        215,
        92,
        52
      ]
    },
    {
      "name": "BidPlaced",
      "discriminator": [
        135,
        53,
        176,
        83,
        193,
        69,
        108,
        61
      ]
    }
  ],
  "errors": [
    {
      "code": 6000,
      "name": "AuctionAlreadyActive"
    },
    {
      "code": 6001,
      "name": "AuctionNotActive"
    },
    {
      "code": 6002,
      "name": "AuctionEnded"
    },
    {
      "code": 6003,
      "name": "BidTooLow"
    },
    {
      "code": 6004,
      "name": "AuctionNotOver"
    },
    {
      "code": 6005,
      "name": "NotTheWinner"
    },
    {
      "code": 6006,
      "name": "AuctionIsActive"
    },
    {
      "code": 6007,
      "name": "MissingBidderAccount"
    },
    {
      "code": 6008,
      "name": "InvalidOldBidderAccount"
    },
    {
      "code": 6009,
      "name": "ContentTooLong"
    }
  ],
  "types": [
    {
      "name": "Auction",
      "type": {
        "kind": "struct",
        "fields": [
          {
            "name": "authority",
            "type": "pubkey"
          },
          {
            "name": "new_content",
            "type": "string"
          },
          {
            "name": "old_content",
            "type": "string"
          },
          {
            "name": "end_timestamp",
            "type": "i64"
          },
          {
            "name": "highest_bid",
            "type": "u64"
          },
          {
            "name": "highest_bidder",
            "type": "pubkey"
          },
          {
            "name": "is_active",
            "type": "bool"
          },
          {
            "name": "bump",
            "type": "u8"
          },
          {
            "name": "old_highest_bid",
            "type": "u64"
          },
          {
            "name": "auction_number",
            "type": "u64"
          }
        ]
      }
    },
    {
      "name": "AuctionEnded",
      "type": {
        "kind": "struct",
        "fields": [
          {
            "name": "winner",
            "type": "pubkey"
          },
          {
            "name": "amount",
            "type": "u64"
          },
          {
            "name": "content",
            "type": "string"
          }
        ]
      }
    },
    {
      "name": "BidPlaced",
      "type": {
        "kind": "struct",
        "fields": [
          {
            "name": "bidder",
            "type": "pubkey"
          },
          {
            "name": "old_bidder",
            "type": "pubkey"
          },
          {
            "name": "amount",
            "type": "u64"
          },
          {
            "name": "new_content",
            "type": "string"
          }
        ]
      }
    }
  ]
}